openlrc/__init__.py
openlrc/agents.py
openlrc/chatbot.py
openlrc/cli.py
openlrc/context.py
openlrc/defaults.py
openlrc/evaluate.py
openlrc/exceptions.py
openlrc/logger.py
openlrc/models.py
openlrc/openlrc.py
openlrc/opt.py
openlrc/preprocess.py
openlrc/prompter.py
openlrc/subtitle.py
openlrc/transcribe.py
openlrc/translate.py
openlrc/utils.py
openlrc/validators.py
openlrc-1.6.1.dist-info/METADATA
openlrc-1.6.1.dist-info/WHEEL
openlrc-1.6.1.dist-info/entry_points.txt
openlrc-1.6.1.dist-info/licenses/LICENSE
openlrc-1.6.1.dist-info/RECORD
