Metadata-Version: 2.4
Name: openlrc
Version: 1.6.1
Summary: Transcribe (whisper) and translate (gpt) voice into LRC file.
Project-URL: Homepage, https://github.com/zh-plus/Open-Lyrics
Project-URL: Bug Tracker, https://github.com/zh-plus/Open-Lyrics/issues
Author-email: Hao Zheng <zhenghaosustc@gmail.com>
License-Expression: MIT
License-File: LICENSE
Keywords: lrc,openai-gpt3,voice transcribe,whisper
Classifier: Intended Audience :: Developers
Classifier: License :: OSI Approved :: MIT License
Classifier: Operating System :: OS Independent
Classifier: Programming Language :: Python :: 3
Classifier: Topic :: Scientific/Engineering
Requires-Python: <3.13,>=3.9
Requires-Dist: aiohttp<4,>=3.9.4
Requires-Dist: anthropic<0.40,>=0.39.0
Requires-Dist: audioread<4,>=3.0.0
Requires-Dist: colorlog<7,>=6.7.0
Requires-Dist: ctranslate2<5,>=4.5.0
Requires-Dist: deepfilternet<0.6,>=0.5.6
Requires-Dist: faster-whisper
Requires-Dist: ffmpeg-normalize<2,>=1.27.5
Requires-Dist: ffmpeg-python<0.3,>=0.2.0
Requires-Dist: filetype<2,>=1.2.0
Requires-Dist: google-genai==1.11.0
Requires-Dist: jaconvv2<0.5,>=0.4
Requires-Dist: json-repair==0.25.2
Requires-Dist: langcodes<4,>=3.3.0
Requires-Dist: language-data~=1.1
Requires-Dist: lingua-language-detector<2,>=1.3.2
Requires-Dist: matplotlib<4,>=3.9.2
Requires-Dist: onnxruntime<2,>=1.20.0
Requires-Dist: openai<2,>=1.55.0
Requires-Dist: pandas<3,>=2.0.2
Requires-Dist: pip>=25.1
Requires-Dist: punctuators<0.0.6,>=0.0.5
Requires-Dist: pysbd<0.4,>=0.3.4
Requires-Dist: soundfile<0.13,>=0.12.1
Requires-Dist: spacy<4,>=3.8.5
Requires-Dist: tiktoken<0.9,>=0.8.0
Requires-Dist: torch>=2.6.0
Requires-Dist: torchaudio>=2.0.0
Requires-Dist: torchvision>=0.21.0
Requires-Dist: tqdm<5,>=4.65.0
Requires-Dist: typing-extensions<5,>=4.12.2
Requires-Dist: zhconv<2,>=1.4.3
